walkman/__init__.py
walkman/_impl.py
walkman-0.0.2.dist-info/METADATA
walkman-0.0.2.dist-info/WHEEL
walkman-0.0.2.dist-info/top_level.txt
walkman-0.0.2.dist-info/RECORD
