Metadata-Version: 2.1
Name: walkman
Version: 0.0.2
Summary: Walkman parsing utilities
Home-page: https://github.com/bakasoft/walkman
Author: Sergio Pedraza
Author-email: sergio.uriel.ph@gmail.com
License: MIT
Platform: UNKNOWN
Classifier: Programming Language :: Python :: 3
Classifier: License :: OSI Approved :: MIT License
Classifier: Operating System :: OS Independent
Requires-Python: >=3.8
